letterboxd_convert/__init__.py
letterboxd_convert/__main__.py
letterboxd_convert/database.py
letterboxd_convert/download.py
letterboxd_convert/parse.py
letterboxd_convert-1.3.dist-info/LICENSE
letterboxd_convert-1.3.dist-info/METADATA
letterboxd_convert-1.3.dist-info/WHEEL
letterboxd_convert-1.3.dist-info/entry_points.txt
letterboxd_convert-1.3.dist-info/top_level.txt
letterboxd_convert-1.3.dist-info/RECORD
