Metadata-Version: 2.1
Name: letterboxd-convert
Version: 1.3
Summary: Convert letterboxd.com lists to a list of IMDb tconsts.
Home-page: https://github.com/gusberinger/letterboxd-convert
Author: Gus Beringer
Author-email: gusberinger@gmail.com
License: UNKNOWN
Project-URL: Bug Tracker, https://github.com/gusberinger/letterboxd-convert/issues
Platform: UNKNOWN
Classifier: Programming Language :: Python :: 3
Classifier: License :: OSI Approved :: MIT License
Classifier: Operating System :: OS Independent
Requires-Python: >=3.6
License-File: LICENSE
Requires-Dist: bs4
Requires-Dist: httpx
